{
  "update_time": "2026-03-05 01:41:30",
  "decision": "加倍定投",
  "reasons": [
    "估值因子得分: 1.36 (PE分位 64.2%)",
    "情绪因子得分: 1.80 (FG指数 10)",
    "趋势因子得分: 1.20 (多头排列，乖离率 4.0%)",
    "综合计算权重: 1.44倍"
  ],
  "individual_decisions": {
    "bias_decision": "1.20x",
    "pe_decision": "1.36x",
    "fg_decision": "1.80x",
    "final_weight": 1.44
  },
  "metrics": {
    "qqq_price": 611.64,
    "ma200": 588.0,
    "bias_percent": 4.02,
    "pe": 33.5801,
    "pe_percentile": 0.6416,
    "fear_greed_score": 10,
    "fear_greed_rating": "Extreme Fear"
  }
}