{
  "NDX": {
    "latest": {
      "update_time": "2026-03-20 14:10:18",
      "decision": "🟢",
      "reasons": [
        "使用动态策略模型: Gemini权衡策略",
        "估值因子得分: 0.75 (PE分位 38.6%)",
        "情绪因子得分: 0.39 (VXN 26.90)",
        "趋势因子得分: 1.95 (乖离率 0.0%)",
        "综合计算权重: 1.00倍"
      ],
      "individual_decisions": {
        "bias_decision": "1.95x",
        "pe_decision": "0.75x",
        "vol_decision": "0.39x",
        "final_weight": 1.0
      },
      "metrics": {
        "price": 24355.28,
        "ma200": 24347.98,
        "bias_percent": 0.03,
        "daily_return_percent": -0.29,
        "pe": 33.1147,
        "pe_percentile": 0.3864,
        "volatility": 26.9,
        "vol_name": "VXN"
      }
    }
  },
  "SP500": {
    "latest": {
      "update_time": "2026-03-20 14:10:18",
      "decision": "🟡",
      "reasons": [
        "使用动态策略模型: 三因子策略",
        "估值因子得分: 0.28 (PE分位 23.7%)",
        "情绪因子得分: 0.46 (VIX 24.06)",
        "趋势因子得分: 1.98 (乖离率 -0.2%)",
        "综合计算权重: 0.84倍"
      ],
      "individual_decisions": {
        "bias_decision": "1.98x",
        "pe_decision": "0.28x",
        "vol_decision": "0.46x",
        "final_weight": 0.84
      },
      "metrics": {
        "price": 6606.49,
        "ma200": 6619.05,
        "bias_percent": -0.19,
        "daily_return_percent": -0.27,
        "pe": 27.4194,
        "pe_percentile": 0.2368,
        "volatility": 24.06,
        "vol_name": "VIX"
      }
    }
  }
}